npc_session/__init__.py
npc_session/parsing.py
npc_session/py.typed
npc_session/records.py
npc_session-0.1.40.dist-info/METADATA
npc_session-0.1.40.dist-info/WHEEL
npc_session-0.1.40.dist-info/top_level.txt
npc_session-0.1.40.dist-info/RECORD
