Metadata-Version: 2.1
Name: npc_session
Version: 0.1.40
Summary: Basic tools for parsing subject, session, date and time associated with data from the Mindscope Neuropixels team, in the cloud.
Author-email: Ben Hardcastle <ben.hardcastle@alleninstitute.org>
License: MIT
Project-URL: Repository, https://github.com/AllenInstitute/npc_session
Project-URL: Issues, https://github.com/AllenInstitute/npc_session/issues
Classifier: Programming Language :: Python :: 3
Classifier: Programming Language :: Python :: 3.9
Classifier: Programming Language :: Python :: 3.10
Classifier: Programming Language :: Python :: 3.11
Classifier: License :: OSI Approved :: MIT License
Classifier: Operating System :: Microsoft :: Windows
Classifier: Operating System :: POSIX :: Linux
Requires-Python: >=3.9
Requires-Dist: typing-extensions>=4.7.1
